README.md
setup.py
dubbo/__init__.py
dubbo/client.py
dubbo/codec/__init__.py
dubbo/codec/decoder.py
dubbo/codec/encoder.py
dubbo/common/__init__.py
dubbo/common/constants.py
dubbo/common/exceptions.py
dubbo/common/loggers.py
dubbo/common/util.py
dubbo/connection/__init__.py
dubbo/connection/connections.py
python_dubbo.egg-info/PKG-INFO
python_dubbo.egg-info/SOURCES.txt
python_dubbo.egg-info/dependency_links.txt
python_dubbo.egg-info/requires.txt
python_dubbo.egg-info/top_level.txt
tests/__init__.py
tests/dubbo_test.py
tests/run_test.py